rt_api/__init__.py
rt_api/api.py
rt_api/constants.py
rt_api/models.py
rt_api-1.1.1.dist-info/METADATA
rt_api-1.1.1.dist-info/RECORD
rt_api-1.1.1.dist-info/WHEEL
rt_api-1.1.1.dist-info/top_level.txt
